botex/__init__.py
botex/bot.py
botex/bot_prompts.csv
botex/botex_db.py
botex/gguf_parser.py
botex/local_llm.py
botex/otree.py
botex-0.1.0.dist-info/LICENSE
botex-0.1.0.dist-info/METADATA
botex-0.1.0.dist-info/WHEEL
botex-0.1.0.dist-info/top_level.txt
botex-0.1.0.dist-info/RECORD
