Metadata-Version: 2.1
Name: botex
Version: 0.1.0
Summary: Using LLMs as Experimental Participants in oTree
Author-email: Joachim Gassen <gassen@wiwi.hu-berlin.de>, Fikir Worku Edossa <edossafi@wiwi.hu-berlin.de>
Maintainer-email: Fikir Worku Edossa <edossafi@wiwi.hu-berlin.de>, Joachim Gassen <gassen@wiwi.hu-berlin.de>
Project-URL: Homepage, https://github.com/joachim-gassen/botex
Project-URL: Issues, https://github.com/joachim-gassen/botex/issues
Classifier: Programming Language :: Python :: 3
Classifier: License :: OSI Approved :: MIT License
Classifier: Operating System :: OS Independent
Classifier: Development Status :: 3 - Alpha
Classifier: Intended Audience :: Science/Research
Classifier: Topic :: Scientific/Engineering :: Artificial Intelligence
Requires-Python: >=3.10
License-File: LICENSE
Requires-Dist: requests
Requires-Dist: psutil
Requires-Dist: selenium
Requires-Dist: litellm
